[
{
  "id": "23",
  "name": "PersonaCortex",
  "icon": "游릴",
  "color": "#FF6B8A",
  "miniAppType": "RN",
  "host": "https://vsa-bucket-public-new.s3.amazonaws.com/miniapps/PersonaCortex/1.0.0.zip",
  "module_name": "PersonaCortexMiniApp",
  "category": "lifestyle",
  "image": "",
  "releaseUrl": "https://vsa-bucket-public-new.s3.amazonaws.com/miniapps/PersonaCortex/1.0.0.zip",
  "hot": false,
  "tag": [
    "游뱔 Createor Love"
  ],
  "score": "游땕 95%"
},
  {
    "id": "1",
    "name": "2048",
    "icon": "游릴",
    "color": "#FF6B8A",
    "miniAppType": "RN",
    "host": "https://vsa-bucket-public-new.s3.amazonaws.com/miniapps/2048/1.0.0.zip",
    "module_name": "2048MiniApp",
    "category": "gaming",
    "image": "https://dzdbhsix5ppsc.cloudfront.net/monster/materials/2048.jpeg",
    "releaseUrl": "https://vsa-bucket-public-new.s3.amazonaws.com/miniapps/2048/1.0.0.zip",
    "hot": false,
    "tag": [
      "游뱔 Createor Love"
    ],
    "score": "游땕 95%"
  },
  {
    "id": "3",
    "name": "FlipMatch",
    "icon": "游릴",
    "color": "#FF6B8A",
    "miniAppType": "RN",
    "host": "https://vsa-bucket-public-new.s3.amazonaws.com/miniapps/FlipMatch/1.0.0.zip",
    "module_name": "FlipMatchMiniApp",
    "category": "gaming",
    "image": "https://dzdbhsix5ppsc.cloudfront.net/monster/materials/memory.jpeg",
    "releaseUrl": "https://vsa-bucket-public-new.s3.amazonaws.com/miniapps/FlipMatch/1.0.0.zip",
    "hot": false,
    "tag": [
      "游뱔 Createor Love"
    ],
    "score": "游땕 97%"
  },
  {
    "id": "4",
    "name": "KidderCrush",
    "icon": "游릴",
    "color": "#FF6B8A",
    "miniAppType": "RN",
    "host": "https://vsa-bucket-public-new.s3.amazonaws.com/miniapps/KidderCrush/1.0.0.zip",
    "module_name": "KidderCrushMiniApp",
    "category": "gaming",
    "image": "https://dzdbhsix5ppsc.cloudfront.net/monster/materials/kidercrush.jpeg",
    "releaseUrl": "https://vsa-bucket-public-new.s3.amazonaws.com/miniapps/KidderCrush/1.0.0.zip",
    "hot": false,
    "tag": [
      "Createor Love"
    ],
    "score": "95%"
  },
  {
    "id": "5",
    "name": "Linker",
    "icon": "游릴",
    "color": "#FF6B8A",
    "miniAppType": "RN",
    "host": "https://vsa-bucket-public-new.s3.amazonaws.com/miniapps/Linker/1.0.0.zip",
    "module_name": "LinkerMiniApp",
    "category": "gaming",
    "image": "https://dzdbhsix5ppsc.cloudfront.net/monster/materials/linker.png",
    "releaseUrl": "https://vsa-bucket-public-new.s3.amazonaws.com/miniapps/Linker/1.0.0.zip",
    "hot": false,
    "tag": [
      "Createor Love"
    ],
    "score": "95%"
  },
  {
    "id": "6",
    "name": "PhotoPuzzle",
    "icon": "游릴",
    "color": "#FF6B8A",
    "miniAppType": "RN",
    "host": "https://vsa-bucket-public-new.s3.amazonaws.com/miniapps/PhotoPuzzle/1.0.0.zip",
    "module_name": "PhotoPuzzleMiniApp",
    "category": "gaming",
    "image": "https://dzdbhsix5ppsc.cloudfront.net/monster/materials/FlipMatch.jpeg",
    "releaseUrl": "https://vsa-bucket-public-new.s3.amazonaws.com/miniapps/PhotoPuzzle/1.0.0.zip",
    "hot": false,
    "tag": [
      "Createor Love"
    ],
    "score": "95%"
  },
  {
    "id": "7",
    "name": "WordleMiniApp",
    "icon": "游릴",
    "color": "#FF6B8A",
    "miniAppType": "RN",
    "host": "https://vsa-bucket-public-new.s3.amazonaws.com/miniapps/WordleMiniApp/1.0.0.zip",
    "module_name": "WordleMiniApp",
    "category": "gaming",
    "image": "https://dzdbhsix5ppsc.cloudfront.net/monster/materials/wordle.jpeg",
    "releaseUrl": "https://vsa-bucket-public-new.s3.amazonaws.com/miniapps/WordleMiniApp/1.0.0.zip",
    "hot": false,
    "tag": [
      "Createor Love"
    ],
    "score": "95%"
  },
  {
    "id": "8",
    "name": "FishyDay",
    "icon": "游릴",
    "color": "#FF6B8A",
    "miniAppType": "RN",
    "host": "https://vsa-bucket-public-new.s3.amazonaws.com/miniapps/FishyDay/1.0.0.zip",
    "module_name": "FishDayMiniApp",
    "category": "gaming",
    "image": "https://dzdbhsix5ppsc.cloudfront.net/monster/materials/FishyDay.png",
    "releaseUrl": "https://vsa-bucket-public-new.s3.amazonaws.com/miniapps/FishyDay/1.0.0.zip",
    "hot": false,
    "tag": [
      "Createor Love"
    ],
    "score": "95%"
  },
  {
    "id": "9",
    "name": "Monex",
    "icon": "游릴",
    "color": "#FF6B8A",
    "miniAppType": "RN",
    "host": "https://vsa-bucket-public-new.s3.amazonaws.com/miniapps/Monex/0.1.0.zip",
    "module_name": "MonexMiniApp",
    "category": "lifestyle",
    "image": "https://dzdbhsix5ppsc.cloudfront.net/monster/materials/monex.png",
    "releaseUrl": "https://vsa-bucket-public-new.s3.amazonaws.com/miniapps/Monex/0.1.0.zip",
    "hot": false,
    "tag": [
      "游뱔 Createor Love"
    ],
    "score": "游땕 95%"
  },
  {
    "id": "10",
    "name": "LeafLens",
    "icon": "游릴",
    "color": "#FF6B8A",
    "miniAppType": "RN",
    "host": "https://vsa-bucket-public-new.s3.amazonaws.com/miniapps/LeafLens/1.0.0.zip",
    "module_name": "LeafLensMiniApp",
    "category": "lifestyle",
    "image": "https://dzdbhsix5ppsc.cloudfront.net/monster/materials/LeafLens.jpg",
    "releaseUrl": "https://vsa-bucket-public-new.s3.amazonaws.com/miniapps/LeafLens/1.0.0.zip",
    "hot": false,
    "tag": [
      "Createor Love"
    ],
    "score": "95%"
  },
  {
    "id": "11",
    "name": "Sudoku",
    "icon": "游릴",
    "color": "#FF6B8A",
    "miniAppType": "H5",
    "host": "https://d3a08sq6vi4p7j.cloudfront.net/",
    "module_name": "SudokuMiniApp",
    "category": "gaming",
    "image": "https://dzdbhsix5ppsc.cloudfront.net/monster/materials/sudoku.jpeg",
    "releaseUrl": "https://d3a08sq6vi4p7j.cloudfront.net/",
    "hot": false,
    "tag": [
      "Createor Love"
    ],
    "score": "95%"
  },
  {
    "id": "12",
    "name": "BlockPuzzle",
    "icon": "游릴",
    "color": "#FF6B8A",
    "miniAppType": "RN",
    "host": "https://vsa-bucket-public-new.s3.amazonaws.com/miniapps/BlockPuzzle/1.0.0.zip",
    "module_name": "BlockPuzzleMiniApp",
    "category": "gaming",
    "image": "https://dzdbhsix5ppsc.cloudfront.net/monster/materials/qblock.jpeg",
    "releaseUrl": "https://vsa-bucket-public-new.s3.amazonaws.com/miniapps/BlockPuzzle/1.0.0.zip",
    "hot": false,
    "tag": [
      "游뱔 Createor Love"
    ],
    "score": "游땕 93%"
  },
  {
    "id": "13",
    "name": "Todo",
    "icon": "游릴",
    "color": "#FF6B8A",
    "miniAppType": "RN",
    "host": "https://vsa-bucket-public-new.s3.amazonaws.com/miniapps/Todo/1.0.0.zip",
    "module_name": "TodoMiniApp",
    "category": "lifestyle",
    "image": "https://dzdbhsix5ppsc.cloudfront.net/monster/todo.jpg",
    "releaseUrl": "https://vsa-bucket-public-new.s3.amazonaws.com/miniapps/Todo/1.0.0.zip",
    "hot": false,
    "tag": [
      "游뱔 Createor Love"
    ],
    "score": "游땕 95%"
  },
  {
    "id": "14",
    "name": "PopPoop",
    "icon": "游릴",
    "color": "#FF6B8A",
    "miniAppType": "RN",
    "host": "https://vsa-bucket-public-new.s3.amazonaws.com/miniapps/PopPoop/1.0.0.zip",
    "module_name": "PopPoopMiniApp",
    "category": "lifestyle",
    "image": "https://dzdbhsix5ppsc.cloudfront.net/monster/poppoop1.jpg",
    "releaseUrl": "https://vsa-bucket-public-new.s3.amazonaws.com/miniapps/PopPoop/1.0.0.zip",
    "hot": false,
    "tag": [
      "游뱔 Createor Love"
    ],
    "score": "游땕 95%"
  },
  {
    "id": "15",
    "name": "Dayer",
    "icon": "游릴",
    "color": "#FF6B8A",
    "miniAppType": "RN",
    "host": "https://vsa-bucket-public-new.s3.amazonaws.com/miniapps/Dayer/1.0.0.zip",
    "module_name": "DayerMiniApp",
    "category": "lifestyle",
    "image": "https://dzdbhsix5ppsc.cloudfront.net/monster/dayer1.jpg",
    "releaseUrl": "https://vsa-bucket-public-new.s3.amazonaws.com/miniapps/Dayer/1.0.0.zip",
    "hot": false,
    "tag": [
      "游뱔 Createor Love"
    ],
    "score": "游땕 95%"
  },
  {
    "id": "16",
    "name": "MoneyTracker",
    "icon": "游릴",
    "color": "#FF6B8A",
    "miniAppType": "RN",
    "host": "https://vsa-bucket-public-new.s3.amazonaws.com/miniapps/MoneyTracker/1.0.0.zip",
    "module_name": "MoneyTrackerMiniApp",
    "category": "lifestyle",
    "image": "https://dzdbhsix5ppsc.cloudfront.net/monster/moneytrack1.jpg",
    "releaseUrl": "https://vsa-bucket-public-new.s3.amazonaws.com/miniapps/MoneyTracker/1.0.0.zip",
    "hot": false,
    "tag": [
      "游뱔 Createor Love"
    ],
    "score": "游땕 95%"
  },
  {
    "id": "17",
    "name": "Lumi",
    "icon": "游릴",
    "color": "#FF6B8A",
    "miniAppType": "RN",
    "host": "https://vsa-bucket-public-new.s3.amazonaws.com/miniapps/Lumi/1.0.0.zip",
    "module_name": "LumiMiniApp",
    "category": "lifestyle",
    "image": "https://dzdbhsix5ppsc.cloudfront.net/monster/lumi.jpg",
    "releaseUrl": "https://vsa-bucket-public-new.s3.amazonaws.com/miniapps/Lumi/1.0.0.zip",
    "hot": false,
    "tag": [
      "游뱔 Createor Love"
    ],
    "score": "游땕 95%"
  },
  {
    "id": "19",
    "name": "Focow",
    "icon": "游릴",
    "color": "#FF6B8A",
    "miniAppType": "RN",
    "host": "https://vsa-bucket-public-new.s3.amazonaws.com/miniapps/Focow/1.0.0.zip",
    "module_name": "FocowMiniApp",
    "category": "lifestyle",
    "image": "https://dzdbhsix5ppsc.cloudfront.net/monster/focow.png",
    "releaseUrl": "https://vsa-bucket-public-new.s3.amazonaws.com/miniapps/Focow/1.0.0.zip",
    "hot": false,
    "tag": [
      "游뱔 Createor Love"
    ],
    "score": "游땕 90%"
  },
  {
    "id": "20",
    "name": "Cosika",
    "icon": "游릴",
    "color": "#FF6B8A",
    "miniAppType": "RN",
    "host": "https://vsa-bucket-public-new.s3.amazonaws.com/miniapps/Cosika/1.0.0.zip",
    "module_name": "CosikaMiniApp",
    "category": "gaming",
    "image": "https://dzdbhsix5ppsc.cloudfront.net/monster/cosika.png",
    "releaseUrl": "https://vsa-bucket-public-new.s3.amazonaws.com/miniapps/Cosika/1.0.0.zip",
    "hot": false,
    "tag": [
      "游뱔 Createor Love"
    ],
    "score": "游땕 95%"
  },
  {
    "id": "21",
    "name": "Drinky",
    "icon": "游릴",
    "color": "#FF6B8A",
    "miniAppType": "RN",
    "host": "https://vsa-bucket-public-new.s3.amazonaws.com/miniapps/Drinky/1.0.0.zip",
    "module_name": "DrinkyMiniApp",
    "category": "lifestyle",
    "image": "https://dzdbhsix5ppsc.cloudfront.net/monster/drinky.jpeg",
    "releaseUrl": "https://vsa-bucket-public-new.s3.amazonaws.com/miniapps/Drinky/1.0.0.zip",
    "hot": false,
    "tag": [
      "游뱔 Createor Love"
    ],
    "score": "游땕 95%"
  },
  {
    "id": "22",
    "name": "Hugglet",
    "icon": "游릴",
    "color": "#FF6B8A",
    "miniAppType": "RN",
    "host": "https://vsa-bucket-public-new.s3.amazonaws.com/miniapps/Hugglet/1.0.0.zip",
    "module_name": "HuggletMiniApp",
    "category": "gaming",
    "image": "https://dzdbhsix5ppsc.cloudfront.net/monster/hugglet.jpeg",
    "releaseUrl": "https://vsa-bucket-public-new.s3.amazonaws.com/miniapps/Hugglet/1.0.0.zip",
    "hot": false,
    "tag": [
      "游뱔 Createor Love"
    ],
    "score": "游땕 98%"
  }
]